{
  "url": "https://utsw.taleo.net/careersection/2/jobdetail.ftl?job=250000NE",
  "data": {
    "success": true,
    "platform": "taleo",
    "description": "Click the link provided to see the complete job description.",
    "requirements": null,
    "responsibilities": null,
    "metadata": {
      "source": "generic",
      "extractionMethod": "meta-tags",
      "url": "https://utsw.taleo.net/careersection/2/jobdetail.ftl?job=250000NE",
      "fetchedAt": "2026-01-24T00:06:19.853Z"
    }
  },
  "cachedAt": 1769213179853
}