{
  "url": "https://jobs.bytedance.com/en/position/7491034443466574087/detail",
  "data": {
    "success": true,
    "platform": "generic",
    "description": "View our opening for Student Researcher Intern (Edge Research Project for General Intelligence — Doubao Foundation Model Team (Seed)) - 2026 Start (PhD) and learn more about what it's like to work at ByteDance!",
    "requirements": null,
    "responsibilities": null,
    "metadata": {
      "source": "generic",
      "extractionMethod": "meta-tags",
      "url": "https://jobs.bytedance.com/en/position/7491034443466574087/detail",
      "fetchedAt": "2025-12-19T20:30:45.598Z"
    }
  },
  "cachedAt": 1766176245598
}