{
  "url": "https://ejia.fa.us6.oraclecloud.com/hcmUI/CandidateExperience/en/sites/CX_1001/job/105781",
  "data": {
    "success": true,
    "platform": "generic",
    "description": "JOB SUMMARY At S&C Electric Company, a 100% employee-owned company, we help keep the lights on for people and businesses worldwide. Our manufacturing roles build the equipment that protects the critical infrastructure of the power grid, and each of our team members lends their unique skills to this crucial mission. We empower our people by providing pathways to a long-term career and support them in their professional growth by sustaining a culture founded on respect, strengthened by collaboration, and measured by our shared successes. The manufacturing industry is booming with opportunities to learn new things, expand your skills, and build a long-term career. Join S&C to make an impact on tomorrow’s energy challenges and become an employee-owner! Available Shift: 1st shift: 8:00 am – 4:30 pm, Monday – Friday Full-Time Winter 2026 Internship Competitive Weekly Pay Period At S&C, we are dedicated to providing competitive and equitable compensation for all our team m...",
    "requirements": null,
    "responsibilities": null,
    "metadata": {
      "source": "generic",
      "extractionMethod": "meta-tags",
      "url": "https://ejia.fa.us6.oraclecloud.com/hcmUI/CandidateExperience/en/sites/CX_1001/job/105781",
      "fetchedAt": "2026-01-01T22:17:00.571Z"
    }
  },
  "cachedAt": 1767305820571
}