{
  "url": "https://berkshiregrey.bamboohr.com/careers/656/",
  "data": {
    "success": true,
    "platform": "generic",
    "description": "As part of the Research &amp; Advanced Development group, you will research and develop new approaches to solving challenging manipulation problems for real-world robotics systems, allowing them to understand and interact with their environment in unprecedented ways. Your work will contribute to enhancin",
    "requirements": null,
    "responsibilities": null,
    "metadata": {
      "source": "generic",
      "extractionMethod": "meta-tags",
      "url": "https://berkshiregrey.bamboohr.com/careers/656/",
      "fetchedAt": "2026-02-04T05:50:45.065Z"
    }
  },
  "cachedAt": 1770184245065
}