{
  "url": "https://www.skydio.com/jobs/7494622003?gh_jid=7494622003",
  "data": {
    "success": true,
    "platform": "generic",
    "description": "{\"@context\":\"http://schema.org\",\"@type\":\"BreadcrumbList\",\"itemListElement\":[{\"@type\":\"ListItem\",\"position\":1,\"item\":{\"@id\":\"https://www.skydio.com/jobs/7494622003\",\"name\":\"Mobile Software Engineer Intern\"}}]} Mobile Software Engineer Intern San Mateo, California, United States Skydio is the leading US drone company and the world leader in autonomous flight, the key technology for the future of drones and aerial mobility. The Skydio team combines deep expertise in artificial intelligence, best-in-class hardware and software product development, operational excellence, and customer obsession to empower a broader, more diverse audience of drone users. From utility inspectors to first responders, soldiers in battlefield scenarios and beyond.About the role: We are looking for interns for Summer 2026. Truly autonomous drones are a new product category that demands a new kind of mobile experience. Forget complex joysticks and awkward tilt-controls: we are crafting completely novel interactions that leverage Skydio’s onboard intelligence to empower a much broader, more diverse audience of drone users. An ideal intern candidate is a senior, or MS-level college student with practical project and/or industry experience developing mobile applications on Android. How you’ll make an impact: Design, prototype, and refine advanced drone interfaces, and then polish a consistent mobile experience for release to the world. Contribute to the development of user interfaces for the world’s most advanced autonomous flying camera. Combine your knowledge of Android ecosystems with our Drone Intelligence API to help create a new gold standard for what a drone app should be. Improve user experiences by incorporating augmented reality, in-app content creation, and sharing capabilities. Iterate on designs based on user feedback, internal testing, and your own experiences piloting Skydio drones. What makes you a good fit: You have a passion for meticulously crafted interfaces that strike the correct balance between ease-of-use, elegance, and power. For Android, we use: Kotlin, Android Studio, Gradle, adb, Linux, and follow best practices for app development using Android Architecture Components and Jetpack Compose Experience in C++ and OpenGL is a big plus. Ability to create tools and automate your workflows using Python scripts You appreciate the value of code-review and other collaborative development practices. Bonus points: You’ve shipped code to the App Store or Google Play store and have experienced the joys (and frustrations) of getting feedback from real users. Experience with IoT or embedded devices using Android NDK Compensation Range: The annual base salary range for this position is $47/hr for Undergrad, $53/hr for Graduate students, and $58 for PhD students*. Compensation will vary based on factors, including skill level, proficiencies, transferable knowledge, and experience. In addition to base salary, Skydio full-time employees are eligible to enroll in our benefit plans and take advantage of a variety of incentives and stipends. *For some positions the pay may be dependent upon the individual's regional location. #LI-AY1 At Skydio we believe that diversity drives innovation. We have created a multidisciplinary environment that embraces the power of diverse perspectives to create elegant solutions for complex problems. We are committed to growing our network of people, programs, and resources to nurture an inclusive culture. Qualified applicants will receive consideration for employment without regard to race, color, religion, sex, sexual orientation, gender identity, national origin, disability, protected veteran status, or other characteristics protected by federal, state or local anti-discrimination laws. For positions located in the United States of America, Skydio, Inc. uses E-Verify to confirm employment eligibility. To learn more about E-Verify, including your rights and responsibilities, please visit https://www.e-verify.gov/",
    "requirements": null,
    "responsibilities": null,
    "metadata": {
      "source": "generic",
      "extractionMethod": "html-selectors",
      "url": "https://www.skydio.com/jobs/7494622003?gh_jid=7494622003",
      "fetchedAt": "2025-12-04T20:50:11.717Z"
    }
  },
  "cachedAt": 1764881411717
}