{
  "url": "https://stripe.com/jobs/search?gh_jid=6558993",
  "data": {
    "success": true,
    "platform": "generic",
    "description": "Help increase the GDP of the internet as part of our Customer Success team.",
    "requirements": null,
    "responsibilities": null,
    "metadata": {
      "source": "generic",
      "extractionMethod": "meta-tags",
      "url": "https://stripe.com/jobs/search?gh_jid=6558993",
      "fetchedAt": "2026-01-19T23:38:52.112Z"
    }
  },
  "cachedAt": 1768865932113
}