{
  "url": "https://jobs.bytedance.com/en/position/7397460004344138021/detail",
  "data": {
    "success": true,
    "platform": "generic",
    "description": "View our opening for Machine Learning Engineer Intern (E-commerce-Supply Chain & Logistics) - 2025 Summer/Fall (PhD) and learn more about what it's like to work at ByteDance!",
    "requirements": null,
    "responsibilities": null,
    "metadata": {
      "source": "generic",
      "extractionMethod": "meta-tags",
      "url": "https://jobs.bytedance.com/en/position/7397460004344138021/detail",
      "fetchedAt": "2025-12-19T20:30:37.965Z"
    }
  },
  "cachedAt": 1766176237965
}