{
  "timestamp": "2026-02-13T10:21:39.772Z",
  "workflow": {
    "last_commit": "2026-02-13 09:57:42 +0000",
    "commit_message": "Update jobs - 2026-02-13"
  },
  "sources": {
    "jsearch": 0,
    "greenhouse": 22,
    "lever": 3,
    "ashby": 0,
    "workday": 5,
    "myworkdayjobs": 121,
    "other": 162,
    "total": 313
  },
  "processing": {
    "current_jobs": 313,
    "seen_jobs_total": 1237,
    "fresh_this_run": 10,
    "pending_queue": 153
  },
  "quota": {
    "jsearch": "18/90",
    "jsearch_remaining": 72
  },
  "databases": {
    "current_jobs_size": "1.8 MB",
    "seen_jobs_size": "80.12 KB",
    "pending_queue_size": "849.47 KB"
  },
  "health": {
    "current_jobs_exists": true,
    "seen_jobs_exists": true,
    "jsearch_usage_exists": true,
    "pending_queue_exists": true
  },
  "warnings": [],
  "errors": []
}